{
    "Name": "ABAP Managed Database Procedures",
    "Description" : "",
    "Content": [
        {
            "Text": "CALL DATABASE PROCEDURE",
            "GitLink": "https://github.com/Xexer/abap-feature-matrix/blob/main/wiki/amdp.md#call-database-procedure",
            "Help": "https://help.sap.com/doc/abapdocu_latest_index_htm/latest/en-US/index.htm?file=abapcall_database_procedure.htm",
            "Release": {
                "7402": "x"
            }
        },
        {
            "Text": "IF_AMDP_MARKER_HDB",
            "GitLink": "",
            "Help": "",
            "Release": {
                "7405": "x"
            }
        },
        {
            "Text": "BY DATABASE PROCEDURE FOR HDB LANGUAGE SQLSCRIPT",
            "GitLink": "",
            "Help": "",
            "Release": {
                "7405": "x"
            }
        },
        {
            "Text": "AMDP BAdIs",
            "GitLink": "",
            "Help": "",
            "Release": {
                "7408": "x"
            }
        },
        {
            "Text": "FOR TABLE FUNCTION",
            "GitLink": "",
            "Help": "",
            "Release": {
                "1511": "x"
            }
        },
        {
            "Text": "Logical Database Schemas",
            "GitLink": "",
            "Help": "",
            "Release": {
                "1610": "x"
            }
        },
        {
            "Text": "Reference to ABAP Types",
            "GitLink": "",
            "Help": "",
            "Release": {
                "1709": "x"
            }
        },
        {
            "Text": "AMDP OPTIONS",
            "GitLink": "",
            "Help": "",
            "Release": {
                "1709": "x"
            }
        },
        {
            "Text": "Logical HDI Containers",
            "GitLink": "",
            "Help": "",
            "Release": {
                "1709": "x"
            }
        },
        {
            "Text": "AMDP Scalar Functions",
            "GitLink": "",
            "Help": "",
            "Release": {
                "1809": "x"
            }
        },
        {
            "Text": "Specifying CDS Entities After USING",
            "GitLink": "",
            "Help": "",
            "Release": {
                "1909": "x"
            }
        }
    ]
}